{"Apple_var1": {"Name": "Himachali apple", "Origin": "Himachal pradesh", "Color": "Red", "Rating": 4.9, "Price per kg": 100}, "Apple_var2": {"Name": "Shimla apple", "Origin": "Shimla", "Color": "Red", "Rating": 4.7, "Price per kg": 85}, "Apple_var3": {"Name": "Green", "Origin": "Australia", "Color": "Green", "Rating": 4.9, "Price per kg": 120}, "Apple_var4": {"Name": "Golden Delicious", "Origin": "USA", "Color": "Pale Yellow", "Rating": 4.8, "Price per kg": 200}, "Apple_var5": {"Name": "Airlie Red Flesh", "Origin": "Oregon", "Color": "Pale Red", "Rating": 4.7, "Price per kg": 150}, "Apple_var6": {"Name": "Fuji", "Origin": "Fujisaki", "Color": "Light Red", "Rating": 4.5, "Price per kg": 75}, "Apple_var7": {"Name": "Cripps Pink", "Origin": "Western Australia", "Color": "Pink-Red", "Rating": 4.7, "Price per kg": 110}, "Apple_var8": {"Name": "Honeycrisp", "Origin": "Twin Cities", "Color": "Pale Red", "Rating": 4.5, "Price per kg": 90}, "Apple_var9": {"Name": "Envy", "Origin": "New Zealand", "Color": "Red", "Rating": 4.9, "Price per kg": 180}, "Apple_var10": {"Name": "Gala", "Origin": "New Zealand", "Color": "Pale Red", "Rating": 4.9, "Price per kg": 250}, "Apple_var11": {"Name": "Pazazz", "Origin": "Minnesota", "Color": "Red", "Rating": 4.2, "Price per kg": 50}, "Apple_var12": {"Name": "Jazz", "Origin": "New Zealand", "Color": "Yellow-Red", "Rating": 4.7, "Price per kg": 150}, "Apple_var13": {"Name": "Red Delicious", "Origin": "Iowa", "Color": "Dark Red", "Rating": 4.9, "Price per kg": 350}, "Apple_var14": {"Name": "Braeburn", "Origin": "New Zealand", "Color": "Pale Red", "Rating": 4.7, "Price per kg": 90}, "Apple_var15": {"Name": "Hidden rose", "Origin": "Oregon", "Color": "vibrant pink", "Rating": 4.9, "Price per kg": 400}, "Mango_var1": {"Name": "Alphonso Mangoes", "Origin": "Maharashtra", "Color": "Reddish green", "Rating": 4.9, "Price per kg": 1000}, "Mango_var2": {"Name": "Kesar Mangoes", "Origin": "Gujarat", "Color": "Light Green", "Rating": 4.8, "Price per kg": 950}, "Mango_var3": {"Name": "Dasheri Mangoes", "Origin": "Uttar Pradesh", "Color": "Green", "Rating": 4.9, "Price per kg": 1200}, "Mango_var4": {"Name": "Himsagar and Kishan Bhog Mangoes", "Origin": " West Bengal", "Color": "Green", "Rating": 4.4, "Price per kg": 750}, "Mango_var5": {"Name": "Chausa Mangoes", "Origin": "Uttar Pradesh", "Color": "Yellow", "Rating": 4.9, "Price per kg": 1000}, "Mango_var6": {"Name": "Badami Mangoes", "Origin": "North Karnataka", "Color": "Yellow green", "Rating": 4.4, "Price per kg": 1000}, "Mango_var7": {"Name": "Safeda Mangoes ", "Origin": "Andhra Pradesh", "Color": "Golden", "Rating": 4.9, "Price per kg": 1500}, "Mango_var8": {"Name": "Fazli Mangoes", "Origin": " Bihar/West Bengal", "Color": "Green", "Rating": 4.5, "Price per kg": 800}, "Mango_var9": {"Name": "Bombay Green Mangoes", "Origin": "Punjab", "Color": "Green", "Rating": 4.9, "Price per kg": 1000}, "Mango_var10": {"Name": "Langra Mangoes", "Origin": "Uttar Pradesh", "Color": "Green", "Rating": 4.8, "Price per kg": 1200}, "Mango_var11": {"Name": "Totapuri Mangoes ", "Origin": "Karnataka", "Color": "Yellow Green", "Rating": 4.9, "Price per kg": 1500}, "Mango_var12": {"Name": "Neelam Mangoes ", "Origin": "Andhra Pradesh", "Color": "Yellow Green", "Rating": 4.9, "Price per kg": 2000}, "Mango_var13": {"Name": "Raspuri Mangoes", "Origin": "Karnataka", "Color": "Green", "Rating": 4.9, "Price per kg": 1700}, "Mango_var14": {"Name": "Mulgoba Mangoes", "Origin": "Tamil Nadu", "Color": "Red Green", "Rating": 4.5, "Price per kg": 1000}, "Mango_var15": {"Name": "Lakshmanbhog Mangoes ", "Origin": "West Bengal", "Color": "Orange", "Rating": 4.9, "Price per kg": 2500}}